sstools/__init__.py
sstools/airbnb.py
sstools/common.py
sstools/lohono.py
sstools/saffronstays.py
sstools/smartflo.py
sstools/vista.py
73e4d8e848405a88f444cff1c9dbc5b8-0.5.dist-info/LICENSE
73e4d8e848405a88f444cff1c9dbc5b8-0.5.dist-info/METADATA
73e4d8e848405a88f444cff1c9dbc5b8-0.5.dist-info/WHEEL
73e4d8e848405a88f444cff1c9dbc5b8-0.5.dist-info/top_level.txt
73e4d8e848405a88f444cff1c9dbc5b8-0.5.dist-info/RECORD
